templaterx/__init__.py
templaterx/components.py
templaterx/exceptions.py
templaterx/helpers/__init__.py
templaterx/helpers/docx.py
templaterx/helpers/jinja.py
templaterx/helpers/structures.py
templaterx/protocols.py
templaterx/py.typed
templaterx/structure.py
templaterx/templaterx.py
templaterx/types.py
templaterx-1.0.0.dist-info/WHEEL
templaterx-1.0.0.dist-info/METADATA
templaterx-1.0.0.dist-info/RECORD
