Metadata-Version: 2.3
Name: templaterx
Version: 1.0.0
Summary: Incremental document rendering for docx templates
Keywords: docx,templating,docxtpl,jinja2,incremental,document-generation,streaming
Author: Matheus Wagner
License: MIT
Classifier: Development Status :: 5 - Production/Stable
Classifier: Intended Audience :: Developers
Classifier: License :: OSI Approved :: MIT License
Classifier: Programming Language :: Python :: 3
Classifier: Programming Language :: Python :: 3 :: Only
Classifier: Programming Language :: Python :: 3.10
Classifier: Programming Language :: Python :: 3.11
Classifier: Programming Language :: Python :: 3.12
Classifier: Programming Language :: Python :: 3.13
Classifier: Programming Language :: Python :: 3.14
Classifier: Topic :: Software Development :: Libraries
Classifier: Topic :: Text Processing
Requires-Dist: docxtpl>=0.20.2
Requires-Dist: jinja2>=3.1.6
Requires-Dist: python-docx>=1.2.0
Requires-Dist: docxcompose>=1.4.0 ; extra == 'subdoc'
Requires-Dist: setuptools>=80.9,<81 ; extra == 'subdoc'
Requires-Python: >=3.10
Project-URL: Homepage, https://github.com/MatheusW166/templaterx
Project-URL: Issues, https://github.com/MatheusW166/templaterx/issues
Project-URL: Repository, https://github.com/MatheusW166/templaterx
Provides-Extra: subdoc
